uubed/__init__.py
uubed/__version__.py
uubed/api.py
uubed/native_wrapper.py
uubed/uubed.py
uubed/encoders/__init__.py
uubed/encoders/eq64.py
uubed/encoders/q64.py
uubed/encoders/shq64.py
uubed/encoders/t8q64.py
uubed/encoders/zoq64.py
uubed-1.0.3.dist-info/METADATA
uubed-1.0.3.dist-info/WHEEL
uubed-1.0.3.dist-info/licenses/LICENSE
uubed-1.0.3.dist-info/RECORD
